{
  "steps": [
    {
      "label":"Score & staff setup",
      "editorLines":6,
      "xpaths": [
        {"rule":"count(//mei:scoreDef) = 1","renderanyway":false,"hint":"You need one scoreDef element."},
        {"rule":"count(//mei:staffGrp) = 1","renderanyway":false,"hint":"You need one staffGroup element."},
        {"rule":"count(//mei:staffDef) = 1","renderanyway":false,"hint":"You need one staffDef element."}
      ],
      "descfile": "102_march_step-01-desc.html",
      "xmlfile": "102_march.01.xml"
    },
    {
      "label":"Score & staff attributes",
      "editorLines":6,
      "xpaths": [
        {"rule":"count(//mei:scoreDef) = 1","renderanyway":false,"hint":"You need one scoreDef element."},
        {"rule":"count(//mei:scoreDef/@*) = 2","renderanyway":false,"hint":"You need two attributes on scoreDef (@key.sig & @meter.sym)."},
        {"rule":"//mei:scoreDef/@key.sig = '3f'","renderanyway":false,"hint":"You need a @key.sig attribute, with a value of 3f."},
        {"rule":"//mei:scoreDef/@meter.sym = 'cut'","renderanyway":false,"hint":"You need an @meter.sym attribute, with a value of cut."},
        {"rule":"count(//mei:staffGrp) = 1","renderanyway":false,"hint":"You need one staffGroup element."},
        {"rule":"count(//mei:staffDef) = 1","renderanyway":false,"hint":"You need one staffDef element."},
        {"rule":"count(//mei:staffDef/@*) = 4","renderanyway":false,"hint":"You need four attributes on staffDef (@n, @lines, @clef.shape & @clef.line)."},
        {"rule":"//mei:staffDef/@n = '1'","renderanyway":false,"hint":"You need a @n attribute, with a value of 1."},
        {"rule":"//mei:staffDef/@lines = '5'","renderanyway":false,"hint":"You need a @lines attribute, with a value of 5."},
        {"rule":"//mei:staffDef/@clef.shape = 'G'","renderanyway":false,"hint":"You need a @clef.shape attribute, with a value of G."},
        {"rule":"//mei:staffDef/@clef.line = '2'","renderanyway":false,"hint":"You need a @clef.line attribute, with a value of 2."}
      ],
      "descfile": "102_march_step-02-desc.html",
      "xmlfile": "102_march.02.xml"
    },
    {
      "label":"Measure setup (empty)",
      "editorLines":7,
      "xpaths": [
        {"rule":"count(//mei:measure) = 1","renderanyway":false,"hint":"You need one measure element."},
        {"rule":"count(//mei:measure/@*) = 1","renderanyway":false,"hint":"You need one attribute on measure (@n)."},
        {"rule":"//mei:measure/@n = '0'","renderanyway":false,"hint":"You need a @n attribute, with a value of 0."},
        {"rule":"count(//mei:staff) = 1","renderanyway":false,"hint":"You need one measure element."},
        {"rule":"count(//mei:staff/@*) = 1","renderanyway":false,"hint":"You need one attribute on measure (@n)."},
        {"rule":"//mei:staff/@n = '0'","renderanyway":false,"hint":"You need a @n attribute, with a value of 0."},
        {"rule":"count(//mei:layer) = 1","renderanyway":false,"hint":"You need one layer element."}
      ],
      "descfile": "102_march_step-03-desc.html",
      "xmlfile": "102_march.03.xml"
    },
    {
      "label":"First note",
      "editorLines":7,
      "xpaths": [
        {"rule":"count(//mei:note) = 1","renderanyway":false,"hint":"You need one note element."},
        {"rule":"count(//mei:note/@*) = 3","renderanyway":false,"hint":"You need three attributes on note (@pname, @oct a& @dur)."},
        {"rule":"//mei:note/@pname = 'b'","renderanyway":false,"hint":"You need a @pname attribute, with a value of c."},
        {"rule":"//mei:note/@oct = '3'","renderanyway":false,"hint":"You need an @oct attribute, with a value of 4."},
        {"rule":"//mei:note/@dur = '4'","renderanyway":false,"hint":"You need a @dur attribute, with a value of 4."}
      ],
      "descfile": "102_march_step-04-desc.html",
      "xmlfile": "102_march.04.xml"
    }
  ],
  "outro":"Congratulations, you've done right."
}